[
  {
    "appId": "2230650",
    "cpu": "Intel Core i5-10200H @ 2.40GHz",
    "duration": "allTheTime",
    "gpu": "Intel Mesa Intel UHD (CML GT1)",
    "gpuDriver": "4.6 Mesa 23.2.1-arch1.2",
    "kernel": "6.5.9-arch2-1",
    "notes": "The game works almost fine!",
    "os": "Arch Linux",
    "protonVersion": "8.0-4",
    "ram": "40 GB",
    "rating": "gold",
    "timestamp": 1704619854,
    "title": "TEVI",
    "source": "protondb"
  },
  {
    "appId": "2230650",
    "cpu": "AMD Custom APU 0405",
    "duration": "unreported",
    "gpu": "AMD Custom GPU 0405 (vangogh, LLVM 13.0.0, DRM 3.45, 5.13.0-valve10.1-1-neptune-02144-g7fffaf925dfb)",
    "gpuDriver": "4.6 Mesa 22.0.0-devel (git-676ccacebc)",
    "kernel": "5.13.0-valve10.1-1-neptune-02144-g7fffaf925dfb",
    "notes": "",
    "os": "SteamOS Holo",
    "protonVersion": "8.0-5",
    "ram": "15 GB",
    "rating": "gold",
    "timestamp": 1711571623,
    "title": "TEVI",
    "source": "protondb"
  },
  {
    "appId": "2230650",
    "cpu": "AMD Ryzen 9 7900X3D 12-Core",
    "duration": "allTheTime",
    "gpu": "AMD Radeon RX 6950 XT (radeonsi, navi21, LLVM 17.0.6, DRM 3.57, 6.8.2-arch2-1)",
    "gpuDriver": "4.6 Mesa 24.0.3-arch1.2",
    "kernel": "6.8.2-arch2-1",
    "notes": "",
    "os": "EndeavourOS Linux",
    "protonVersion": "8.0-5",
    "ram": "31 GB",
    "rating": "gold",
    "timestamp": 1712443043,
    "title": "TEVI",
    "source": "protondb"
  },
  {
    "appId": "2230650",
    "cpu": "AMD Ryzen 5 3600 6-Core",
    "duration": "oneToFourHours",
    "gpu": "NVIDIA GeForce GTX 1660 SUPER",
    "gpuDriver": "NVIDIA 560.35.03",
    "kernel": "6.6.63",
    "notes": "Works flawlessly out of the box",
    "os": "NixOS 25.05 (Warbler)",
    "protonVersion": "9.0-4",
    "ram": "16 GB",
    "rating": "platinum",
    "timestamp": 1735086614,
    "title": "TEVI",
    "source": "protondb"
  }
]