[
  {
    "appId": "402710",
    "cpu": "AMD Ryzen 7 1800X Eight-Core",
    "duration": "aboutAnHour",
    "gpu": "NVIDIA GeForce GTX 1080",
    "gpuDriver": "NVIDIA 415.27",
    "kernel": "4.12.14-lp150.12.45-default",
    "notes": "You'll need to manually install dinput to do any action in game. Also the FPS are somehow low at maximum settings ( ~ 40)",
    "os": "openSUSE Leap 15.0",
    "protonVersion": "Beta (3.16-6)",
    "ram": "16 GB",
    "rating": "Silver",
    "timestamp": 1549323184,
    "title": "Osiris: New Dawn",
    "source": "protondb"
  },
  {
    "appId": "402710",
    "cpu": "Intel Core i7-7700K @ 4.20GHz",
    "duration": "aboutAnHour",
    "gpu": "NVIDIA GeForce GTX 1080 Ti",
    "gpuDriver": "NVIDIA 418.43",
    "kernel": "4.19.32-1-MANJARO",
    "notes": "Works out of the box. None of the previous stutters or FPS drops are present anymore. This runs just as good, or bad, as on Windows. FPS between 60 - 144. ",
    "os": "Manjaro Linux",
    "protonVersion": "4.2-2",
    "protonVersionManual": "4.2-2",
    "ram": "32 GB",
    "rating": "Platinum",
    "timestamp": 1555516320,
    "title": "Osiris: New Dawn",
    "source": "protondb"
  },
  {
    "appId": "402710",
    "cpu": "AMD FX-6300 Six-Core",
    "duration": "lessThanFifteenMinutes",
    "gpu": "NVIDIA GeForce GTX 1050 Ti",
    "gpuDriver": "NVIDIA 418.43",
    "kernel": "4.14.52-gentoo",
    "notes": "Previous versions of Proton and Wine seemed to have problems with accepting keyboard output.  As of (at least) Proton 4.2-5, there seems to be no more problems running the game out-of-the-box.",
    "os": "Gentoo Base System release 2.6",
    "protonVersion": "Default",
    "ram": "16 GB",
    "rating": "Platinum",
    "timestamp": 1558818473,
    "title": "Osiris: New Dawn",
    "source": "protondb"
  },
  {
    "appId": "402710",
    "cpu": "Intel Core i7-7700K @ 4.20GHz",
    "duration": "lessThanAnHour",
    "gpu": "NVIDIA GeForce GTX 1070",
    "gpuDriver": "NVIDIA 418.56",
    "kernel": "4.15.0-51-generic",
    "notes": "Keyboard inputs now work; game appears to run fine.",
    "os": "Linux Mint 18.3 Sylvia",
    "protonVersion": "4.2-7",
    "ram": "32 GB",
    "rating": "Platinum",
    "timestamp": 1560496268,
    "title": "Osiris: New Dawn",
    "source": "protondb"
  }
]