[
  {
    "appId": "559650",
    "cpu": "AMD Ryzen 7 1700 Eight-Core",
    "duration": "aboutAnHour",
    "gpu": "Radeon RX 580",
    "gpuDriver": "4.5 Mesa 18.3.1",
    "kernel": "4.19.9-105.current",
    "notes": "Alt tab, graphics changes, online, everything I've tested works out of the box. Can hit 60fps without any modifications.",
    "os": "Solus",
    "protonVersion": "Default",
    "ram": "16 GB",
    "rating": "Platinum",
    "timestamp": 1546658411,
    "title": "Witch It",
    "source": "protondb"
  },
  {
    "appId": "559650",
    "cpu": "Intel Core i7-6700K @ 4.00GHz",
    "duration": "severalHours",
    "gpu": "Radeon RX 570",
    "gpuDriver": "4.5 Mesa 18.3.1",
    "kernel": "4.20.3-arch1-1-ARCH",
    "notes": "didn't start in i3wm;\nruns perfect with lxde;\n\nmultiplayer works without problem;\nno audio issues here;",
    "os": "Linux 4.x",
    "protonVersion": "Beta (3.16-6)",
    "ram": "16 GB",
    "rating": "Gold",
    "timestamp": 1552516037,
    "title": "Witch It",
    "source": "protondb"
  },
  {
    "appId": "559650",
    "cpu": "Intel Core i7-8750H @ 2.20GHz",
    "duration": "aboutAnHour",
    "gpu": "NVIDIA GeForce GTX 1060",
    "gpuDriver": "NVIDIA 418.56",
    "kernel": "5.0.8-050008-generic",
    "notes": "Runs just fine without tweaks.",
    "os": "Pop!_OS 18.10",
    "protonVersion": "Default",
    "ram": "16 GB",
    "rating": "Platinum",
    "timestamp": 1555665434,
    "title": "Witch It",
    "source": "protondb"
  },
  {
    "appId": "559650",
    "cpu": "Intel Core i5-6500 @ 3.20GHz",
    "duration": "lessThanFifteenMinutes",
    "gpu": "Radeon RX 580",
    "gpuDriver": "4.5 Mesa 19.0.2",
    "kernel": "5.1.0-050100rc5-generic",
    "notes": "dont start at all",
    "os": "Kubuntu 19.04",
    "protonVersion": "Default",
    "ram": "16 GB",
    "rating": "Borked",
    "timestamp": 1555712833,
    "title": "Witch It",
    "source": "protondb"
  },
  {
    "appId": "559650",
    "cpu": "Intel Core i7-6700K @ 4.00GHz",
    "duration": "severalHours",
    "gpu": "NVIDIA GeForce GTX 1080",
    "gpuDriver": "NVIDIA 418.56",
    "kernel": "5.0.7-arch1-1-ARCH",
    "notes": "i3wm. As far as I can tell, the game runs really well and seemingly no issues in the few hours I played with friends. Thx devs! I'll  think about picking this one up after a native build!",
    "os": "Arch Linux",
    "protonVersion": "4.2-3",
    "protonVersionManual": "4.2-3",
    "ram": "32 GB",
    "rating": "Platinum",
    "timestamp": 1555800444,
    "title": "Witch It",
    "source": "protondb"
  },
  {
    "appId": "559650",
    "cpu": "Intel Core i5-8400 @ 2.80GHz",
    "duration": "severalHours",
    "gpu": "NVIDIA GeForce GTX 1060 6GB",
    "gpuDriver": "NVIDIA 430.26",
    "kernel": "5.2.2-1-MANJARO",
    "notes": "launch without the intro video and everything is fine",
    "os": "Manjaro Linux",
    "protonVersion": "4.2-5",
    "protonVersionManual": "4.2-5",
    "ram": "16 GB",
    "rating": "Gold",
    "timestamp": 1565277323,
    "title": "Witch It",
    "source": "protondb"
  },
  {
    "appId": "559650",
    "cpu": "Intel Core i5-8300H @ 2.30GHz",
    "duration": "aboutAnHour",
    "gpu": "NVIDIA GeForce GTX 1050",
    "gpuDriver": "NVIDIA 430.26",
    "kernel": "5.0.0-23-generic",
    "notes": "The gameplay itself is smooth, however the ingame tutorial videos and intro cutscenes won't play, opening the chat also causes the game to crash.",
    "os": "Linux Mint 19.2 Tina",
    "protonVersion": "Default",
    "ram": "8 GB",
    "rating": "Silver",
    "timestamp": 1565378236,
    "title": "Witch It",
    "source": "protondb"
  }
]