[
  {
    "appId": "448280",
    "cpu": "Intel Core i7-4770K @ 3.50GHz",
    "duration": "lessThanAnHour",
    "gpu": "NVIDIA GeForce GTX 970",
    "gpuDriver": "NVIDIA 410.78",
    "kernel": "4.18.0-13-generic",
    "notes": "Had to use 'PROTON_USE_WINED3D11=1 %command%` in my launch options, as well as use a proton beta branch, but afterwards the only thing I found not working was fluid rendering when pouring from bottles",
    "os": "Pop!_OS 18.10",
    "protonVersion": "Beta (3.16-6)",
    "ram": "16 GB",
    "rating": "Silver",
    "timestamp": 1547471825,
    "title": "Job Simulator",
    "tweaks": {
      "useWineD3d11": true
    },
    "source": "protondb"
  },
  {
    "appId": "448280",
    "cpu": "AMD Ryzen 7 1700 Eight-Core",
    "duration": "severalHours",
    "gpu": "Radeon RX 580",
    "gpuDriver": "4.4 Mesa 18.2.8",
    "kernel": "4.18.0-15-generic",
    "notes": "By default, could not see hands. Adding PROTON_USE_WINED3D=1 option showed the hands",
    "os": "Pop!_OS 18.10",
    "protonVersion": "Beta (3.16-7)",
    "ram": "16 GB",
    "rating": "Gold",
    "timestamp": 1551505243,
    "title": "Job Simulator",
    "source": "protondb"
  },
  {
    "appId": "448280",
    "cpu": "AMD Ryzen 3 2200G with Radeon Vega Graphics",
    "duration": "severalHours",
    "gpu": "NVIDIA GeForce GTX 1060 6GB",
    "gpuDriver": "NVIDIA 418.56",
    "kernel": "4.18.0-20-generic",
    "notes": "Runs great out of the box, didn't need to set or change anything",
    "os": "Ubuntu 18.04.2 LTS",
    "protonVersion": "4.2-4",
    "ram": "16 GB",
    "rating": "Platinum",
    "timestamp": 1561566139,
    "title": "Job Simulator",
    "source": "protondb"
  },
  {
    "appId": "448280",
    "cpu": "Intel Core i7-7700 @ 3.60GHz",
    "duration": "aboutAnHour",
    "gpu": "AMD Radeon VII",
    "gpuDriver": "4.5 Mesa 19.0.6",
    "kernel": "5.1.14-121.current",
    "notes": "Game ran just fine, no tweaks, but the computer locked up when exiting",
    "os": "Solus",
    "protonVersion": "Default",
    "ram": "16 GB",
    "rating": "Platinum",
    "timestamp": 1562211535,
    "title": "Job Simulator",
    "source": "protondb"
  },
  {
    "appId": "448280",
    "cpu": "Intel Core i7-7700K @ 4.20GHz",
    "duration": "lessThanAnHour",
    "gpu": "NVIDIA GeForce GTX 1080 Ti",
    "gpuDriver": "NVIDIA 418.52.18",
    "kernel": "5.2.8-arch1-1-ARCH",
    "notes": "Runs perfectly with my Vive.",
    "os": "Arch Linux",
    "protonVersion": "4.11-2",
    "ram": "16 GB",
    "rating": "Platinum",
    "timestamp": 1565550181,
    "title": "Job Simulator",
    "source": "protondb"
  },
  {
    "appId": "448280",
    "cpu": "Intel Xeon E5-1650 v2 @ 3.50GHz",
    "duration": "lessThanFifteenMinutes",
    "gpu": "NVIDIA GeForce GTX 1070",
    "gpuDriver": "NVIDIA 430.40",
    "kernel": "4.19.57-gentoo",
    "os": "Gentoo Base System release 2.6",
    "protonVersion": "4.11-2",
    "protonVersionManual": "3.16-4",
    "ram": "64 GB",
    "rating": "Platinum",
    "timestamp": 1566598435,
    "title": "Job Simulator",
    "source": "protondb"
  }
]