[
  {
    "appId": "485600",
    "cpu": "Intel Core m3-7Y30 @ 1.00GHz",
    "duration": "unreported",
    "gpu": "Intel Mesa Intel HD 615 (KBL GT2)",
    "gpuDriver": "4.6 Mesa 21.3.4",
    "kernel": "5.13.0-valve10.1-1-neptune-02144-g7fffaf925dfb",
    "notes": "Launching the game just caused SteamOS3 to reload back to main menu.",
    "os": "SteamOS Holo",
    "protonVersion": "7.0-1",
    "ram": "8 GB",
    "rating": "borked",
    "timestamp": 1646636025,
    "title": "",
    "source": "protondb"
  }
]