[
  {
    "appId": "867210",
    "cpu": "AMD Ryzen 7 9800X3D 8-Core",
    "duration": "allTheTime",
    "gpu": "AMD Radeon RX 9070 XT (radeonsi, gfx1201, ACO, DRM 3.64, 6.18.7-76061807-generic)",
    "gpuDriver": "4.6 Mesa 25.1.5-1pop0~1753463422~24.04~8af185e",
    "kernel": "6.18.7-76061807-generic",
    "notes": "",
    "os": "Pop!_OS 24.04 LTS",
    "protonVersion": "10.0-3",
    "ram": "31 GB",
    "rating": "gold",
    "timestamp": 1772105706,
    "title": "",
    "source": "protondb"
  },
  {
    "appId": "867210",
    "cpu": "AMD Ryzen 7 7800X3D 8-Core",
    "duration": "severalHours",
    "gpu": "NVIDIA GeForce RTX 4070 Ti SUPER",
    "gpuDriver": "NVIDIA 590.48.01",
    "kernel": "6.18.2-3-cachyos",
    "notes": "Works ootb",
    "os": "CachyOS",
    "protonVersion": "10.0-3",
    "ram": "31 GB",
    "rating": "gold",
    "timestamp": 1772402853,
    "title": "",
    "source": "protondb"
  },
  {
    "appId": "867210",
    "cpu": "AMD Ryzen 7 8745H w/ Radeon 780M Graphics",
    "duration": "severalHours",
    "gpu": "AMD Radeon 780M (radeonsi, phoenix, LLVM 20.1.2, DRM 3.61, 6.14.0-37-generic)",
    "gpuDriver": "4.6 Mesa 25.2.8-0ubuntu0.24.04.1",
    "kernel": "6.14.0-37-generic",
    "notes": "Try to switch to GE-Proton in case of any issues with cutscenes.",
    "os": "Linux Mint 22.3",
    "protonVersion": "10.0-3",
    "ram": "24 GB",
    "rating": "gold",
    "timestamp": 1778942505,
    "title": "",
    "source": "protondb"
  },
  {
    "appId": "867210",
    "cpu": "AMD Ryzen 5 4600G with Radeon Graphics",
    "duration": "severalHours",
    "gpu": "AMD Radeon RX 560 (radeonsi, polaris11, ACO, DRM 3.61, 6.12.57+deb13-amd64)",
    "gpuDriver": "4.6 Mesa 25.0.7-2",
    "kernel": "6.12.57+deb13-amd64",
    "notes": "",
    "os": "Debian GNU/Linux 13 (trixie)",
    "protonVersion": "10.0-3",
    "ram": "31 GB",
    "rating": "gold",
    "timestamp": 1779215326,
    "title": "",
    "source": "protondb"
  }
]