[
  {
    "appId": "1318420",
    "cpu": "Intel Core i7-3770K @ 3.50GHz",
    "duration": "unreported",
    "gpu": "NVIDIA GeForce GTX 1060 6GB",
    "gpuDriver": "NVIDIA 440.64",
    "kernel": "5.4.0-25-lowlatency",
    "notes": "When I start the game from the main menu, I can see a loading screen for a split second, then the screen goes black and nothing happens.",
    "os": "Ubuntu 20.04 LTS",
    "protonVersion": "5.0-7",
    "ram": "16 GB",
    "rating": "borked",
    "timestamp": 1590939308,
    "title": "",
    "source": "protondb"
  },
  {
    "appId": "1318420",
    "cpu": "Intel Core i7-4790K @ 4.00GHz",
    "duration": "unreported",
    "gpu": "NVIDIA GeForce GTX 1660 SUPER",
    "gpuDriver": "NVIDIA 440.64",
    "kernel": "5.4.0-33-generic",
    "notes": "Black Screen",
    "os": "Ubuntu 20.04 LTS",
    "protonVersion": "5.0-7",
    "ram": "8 GB",
    "rating": "borked",
    "timestamp": 1591055370,
    "title": "",
    "source": "protondb"
  },
  {
    "appId": "1318420",
    "cpu": "Intel Core i7-3930K @ 3.20GHz",
    "duration": "unreported",
    "gpu": "Radeon RX 590",
    "gpuDriver": "4.6 Mesa 20.0.4",
    "kernel": "5.4.0-7629-generic",
    "notes": "Black Screen after Main Menu",
    "os": "Pop!_OS 20.04 LTS",
    "protonVersion": "5.0-7",
    "ram": "64 GB",
    "rating": "borked",
    "timestamp": 1591324713,
    "title": "",
    "source": "protondb"
  },
  {
    "appId": "1318420",
    "cpu": "Intel Core i7-3820 @ 3.60GHz",
    "duration": "unreported",
    "gpu": "NVIDIA GeForce GTX 1660 Ti",
    "gpuDriver": "NVIDIA 440.82",
    "kernel": "5.4.31-1-MANJARO",
    "notes": "Black screen after selecting start on main menu",
    "os": "Manjaro Linux",
    "protonVersion": "5.0-8",
    "ram": "16 GB",
    "rating": "borked",
    "timestamp": 1591471919,
    "title": "",
    "source": "protondb"
  },
  {
    "appId": "1318420",
    "cpu": "Intel Core i7-4790K @ 4.00GHz",
    "duration": "unreported",
    "gpu": "NVIDIA GeForce GTX 1080",
    "gpuDriver": "NVIDIA 440.82",
    "kernel": "5.7.2-arch1-1",
    "notes": "Hangs on intro video with a black screen on vanilla proton. Works perfectly, including video with Proton-GE",
    "os": "Arch Linux",
    "protonVersion": "5.0-9",
    "ram": "16 GB",
    "rating": "gold",
    "timestamp": 1591973961,
    "title": "",
    "source": "protondb"
  },
  {
    "appId": "1318420",
    "cpu": "AMD Ryzen 7 1800X Eight-Core",
    "duration": "unreported",
    "gpu": "AMD Radeon R9 380",
    "gpuDriver": "4.6 Mesa 20.0.4",
    "kernel": "5.4.0-37-generic",
    "notes": "Using Proton-GE fixes the black screen. After that everyting in the game works. (Played until the end of the Prologue)",
    "os": "Ubuntu 20.04 LTS",
    "protonVersion": "5.0-9",
    "ram": "32 GB",
    "rating": "gold",
    "timestamp": 1592334669,
    "title": "",
    "source": "protondb"
  },
  {
    "appId": "1318420",
    "cpu": "AMD Ryzen 5 2600 Six-Core",
    "duration": "unreported",
    "gpu": "NVIDIA GeForce GTX 1060 6GB",
    "gpuDriver": "NVIDIA 440.82",
    "kernel": "5.6.16-1-MANJARO",
    "notes": "",
    "os": "Manjaro Linux",
    "protonVersion": "5.0-9",
    "ram": "32 GB",
    "rating": "gold",
    "timestamp": 1593272779,
    "title": "",
    "source": "protondb"
  },
  {
    "appId": "1318420",
    "cpu": "Intel Core i5-7500 @ 3.40GHz",
    "duration": "unreported",
    "gpu": "NVIDIA GeForce GTX 1060 6GB",
    "gpuDriver": "NVIDIA 440.100",
    "kernel": "4.15.0-109-generic",
    "notes": "With the latest Proton-GE (5.11-GE-2-MF) the game runs flawless except it freezes on Alt-Tab.\nCould play the whole demo without issues.",
    "os": "KDE neon User Edition 5.19",
    "protonVersion": "5.0-9",
    "ram": "8 GB",
    "rating": "gold",
    "timestamp": 1593685759,
    "title": "",
    "source": "protondb"
  },
  {
    "appId": "1318420",
    "cpu": "Intel Core i5-4590 @ 3.30GHz",
    "duration": "unreported",
    "gpu": "NVIDIA GeForce GTX 960",
    "gpuDriver": "NVIDIA 440.100",
    "kernel": "5.6.19-2-MANJARO",
    "notes": "",
    "os": "Manjaro Linux",
    "protonVersion": "5.0-9",
    "ram": "8 GB",
    "rating": "gold",
    "timestamp": 1599096112,
    "title": "",
    "source": "protondb"
  }
]