[
  {
    "appId": "573090",
    "cpu": "AMD A8-3850 APU with Radeon HD Graphics",
    "duration": "aboutAnHour",
    "gpu": "NVIDIA GeForce GTX 650 Ti BOOST",
    "gpuDriver": "NVIDIA 415.27",
    "kernel": "4.15.0-46-generic",
    "notes": "EA build 0.5.23 - everything works great, as if native. runs exactly as on Windows. ",
    "os": "Ubuntu 18.04.2 LTS",
    "protonVersion": "Beta (3.16-6)",
    "ram": "8 GB",
    "rating": "Platinum",
    "timestamp": 1550983477,
    "title": "Stormworks: Build and Rescue",
    "source": "protondb"
  },
  {
    "appId": "573090",
    "cpu": "Intel Core i7-8700 @ 3.20GHz",
    "duration": "aboutAnHour",
    "gpu": "NVIDIA GeForce RTX 2070",
    "gpuDriver": "NVIDIA 418.56",
    "kernel": "4.18.0-18-generic",
    "notes": "Runs as good or better than windows",
    "os": "Ubuntu 18.04.2 LTS",
    "protonVersion": "4.2-3",
    "protonVersionManual": "4.2-3",
    "ram": "32 GB",
    "rating": "Platinum",
    "timestamp": 1556514181,
    "title": "Stormworks: Build and Rescue",
    "source": "protondb"
  },
  {
    "appId": "573090",
    "cpu": "Intel Core i5-8500 @ 3.00GHz",
    "duration": "severalHours",
    "gpu": "NVIDIA GeForce GTX 1070",
    "gpuDriver": "NVIDIA 430.14",
    "kernel": "4.15.0-50-generic",
    "notes": "Played Campaign for several hours, runs perfectly!",
    "os": "Linux Mint 19 Tara",
    "protonVersion": "4.2-6",
    "ram": "16 GB",
    "rating": "Platinum",
    "timestamp": 1560094320,
    "title": "Stormworks: Build and Rescue",
    "source": "protondb"
  },
  {
    "appId": "573090",
    "cpu": "Intel Core i9-9900K @ 3.60GHz",
    "duration": "aboutAnHour",
    "gpu": "Intel UHD 630 (Coffeelake 3x8 GT2)",
    "gpuDriver": "3.0 Mesa 19.1.1",
    "kernel": "5.1.15-arch1-1-ARCH",
    "notes": "Launch options must be set in order to bypass Mesa3Ds default OpenGL 3.0 context. This is what I used:\n\n MESA_GL_VERSION_OVERRIDE=4.5 MESA_GLSL_VERSION_OVERRIDE=450 %command%",
    "os": "Unknown",
    "protonVersion": "Default",
    "ram": "16 GB",
    "rating": "Gold",
    "timestamp": 1562271086,
    "title": "Stormworks: Build and Rescue",
    "source": "protondb"
  },
  {
    "appId": "573090",
    "cpu": "Intel Core i5-4460S @ 2.90GHz",
    "duration": "lessThanFifteenMinutes",
    "gpu": "Radeon 550",
    "gpuDriver": "4.5 Mesa 19.1.3 - SteamVR PPA",
    "kernel": "5.2.5-steamvr-generic",
    "notes": "Crashes as soon as the window pops up. (Potentially linked with the fact i have an amd graphics card)",
    "os": "Linux Mint 19.1 Tessa (64\u00a0bits)",
    "protonVersion": "4.11-1",
    "ram": "8 GB",
    "rating": "Borked",
    "timestamp": 1564738907,
    "title": "Stormworks: Build and Rescue",
    "source": "protondb"
  },
  {
    "appId": "573090",
    "cpu": "AMD A8-3850 APU with Radeon HD Graphics",
    "duration": "lessThanAnHour",
    "gpu": "NVIDIA GeForce GTX 650 Ti BOOST",
    "gpuDriver": "NVIDIA 430.40",
    "kernel": "5.0.0-23-generic",
    "notes": "Current game build 0.7.24 - like all previous builds, it runs perfectly out of the gate. Windowed or Fullscreen. Maxed out graphics or medium/low. No issues.",
    "os": "Ubuntu 19.04",
    "protonVersion": "4.2-9",
    "ram": "8 GB",
    "rating": "Platinum",
    "timestamp": 1564845974,
    "title": "Stormworks: Build and Rescue",
    "source": "protondb"
  },
  {
    "appId": "573090",
    "cpu": "Intel Core i5-4460S @ 2.90GHz",
    "duration": "moreThanTenHours",
    "gpu": "Radeon 550",
    "gpuDriver": "4.5 Mesa 19.1.5 - SteamVR PPA",
    "kernel": "5.2.9-steamvr-generic",
    "notes": "No longer crash on startup since last update. Works without any issues.",
    "os": "Linux Mint 19.2 Tina (64\u00a0bits)",
    "protonVersion": "4.11-3",
    "protonVersionManual": "4.11-3",
    "ram": "8 GB",
    "rating": "Platinum",
    "timestamp": 1566934064,
    "title": "Stormworks: Build and Rescue",
    "source": "protondb"
  },
  {
    "appId": "573090",
    "cpu": "Intel Core i5-9600K @ 3.70GHz",
    "duration": "lessThanAnHour",
    "gpu": "NVIDIA GeForce RTX 2080",
    "gpuDriver": "NVIDIA 418.88",
    "kernel": "5.2.11-1-MANJARO",
    "os": "Manjaro Linux (64\u00a0bits)",
    "protonVersion": "Default",
    "ram": "16 GB",
    "rating": "Platinum",
    "timestamp": 1570448093,
    "title": "Stormworks: Build and Rescue",
    "source": "protondb"
  },
  {
    "appId": "573090",
    "cpu": "AMD A8-3850 APU with Radeon HD Graphics",
    "duration": "aboutAnHour",
    "gpu": "Ubuntu 19.04 (64 bit)",
    "gpuDriver": "Linux",
    "kernel": "5.0.0-32-generic",
    "notes": "latest build 0.9.3 - runs like native, with all the new, additional graphic settings features to the max. ",
    "os": "AuthenticAMD",
    "protonVersion": "4.11-6",
    "ram": "Realtek ALC892",
    "rating": "Platinum",
    "timestamp": 1571266081,
    "title": "Stormworks: Build and Rescue",
    "source": "protondb"
  }
]