[
  {
    "appId": "2639810",
    "cpu": "AMD Ryzen 5 5600G with Radeon Graphics",
    "duration": "unreported",
    "gpu": "AMD Radeon (radeonsi, renoir, LLVM 15.0.7, DRM 3.54, 6.5.0-26-generic)",
    "gpuDriver": "4.6 Mesa 24.0.4 - kisak-mesa PPA",
    "kernel": "6.5.0-26-generic",
    "notes": "Requires minimal tinkering to play.",
    "os": "Ubuntu 22.04.4 LTS",
    "protonVersion": "8.0-4",
    "ram": "12 GB",
    "rating": "platinum",
    "timestamp": 1713900270,
    "title": "",
    "source": "protondb"
  },
  {
    "appId": "2639810",
    "cpu": "AMD FX-6300 Six-Core",
    "duration": "oneToFourHours",
    "gpu": "NVIDIA GeForce GTX 660",
    "gpuDriver": "NVIDIA 470.239.06",
    "kernel": "6.8.1-273-tkg-eevdf",
    "notes": "Game runs perfectly whether OOTB with Proton 8 or with Proton GE.",
    "os": "Arch Linux",
    "protonVersion": "8.0-5",
    "ram": "16 GB",
    "rating": "platinum",
    "timestamp": 1713936656,
    "title": "",
    "source": "protondb"
  },
  {
    "appId": "2639810",
    "cpu": "AMD Custom APU 0405",
    "duration": "unreported",
    "gpu": "AMD Custom GPU 0405 (vangogh, LLVM 14.0.6, DRM 3.45, 5.13.0-valve36-1-neptune)",
    "gpuDriver": "4.6 (Compatibility Profile) Mesa 22.2.0 (git-17e5312102)",
    "kernel": "5.13.0-valve36-1-neptune",
    "notes": "Plays great on SD. No problems so far",
    "os": "SteamOS Holo",
    "protonVersion": "8.0-5",
    "ram": "15 GB",
    "rating": "gold",
    "timestamp": 1714152290,
    "title": "",
    "source": "protondb"
  },
  {
    "appId": "2639810",
    "cpu": "11th Gen Intel Core i5-11500 @ 2.70GHz",
    "duration": "unreported",
    "gpu": "NVIDIA GeForce GTX 1650",
    "gpuDriver": "NVIDIA 545.29.06",
    "kernel": "5.15.0-105-generic",
    "notes": "Runs very smoothly for me",
    "os": "Linux Mint 21.3",
    "protonVersion": "8.0-4",
    "ram": "32 GB",
    "rating": "platinum",
    "timestamp": 1714488392,
    "title": "",
    "source": "protondb"
  },
  {
    "appId": "2639810",
    "cpu": "AMD Ryzen 5 6600H with Radeon Graphics",
    "duration": "allTheTime",
    "gpu": "NVIDIA GeForce RTX 3050 Laptop GPU",
    "gpuDriver": "NVIDIA 535.171.04",
    "kernel": "6.5.0-28-generic",
    "notes": "Runs flawlessly out of the box, no tinkering needed.",
    "os": "Ubuntu 23.10",
    "protonVersion": "9.0-1",
    "ram": "15 GB",
    "rating": "gold",
    "timestamp": 1715115515,
    "title": "",
    "source": "protondb"
  },
  {
    "appId": "2639810",
    "cpu": "AMD Custom APU 0405",
    "duration": "oneToFourHours",
    "gpu": "AMD Custom GPU 0405 (vangogh, LLVM 14.0.6, DRM 3.45, 5.13.0-valve36-1-neptune)",
    "gpuDriver": "4.6 (Compatibility Profile) Mesa 22.2.0 (git-17e5312102)",
    "kernel": "5.13.0-valve36-1-neptune",
    "notes": "Runs great OOTB with no problems whatsoever.",
    "os": "SteamOS Holo",
    "protonVersion": "9.0-1",
    "ram": "15 GB",
    "rating": "gold",
    "timestamp": 1715129085,
    "title": "",
    "source": "protondb"
  },
  {
    "appId": "2639810",
    "cpu": "AMD Custom APU 0405",
    "duration": "severalHours",
    "gpu": "AMD Custom GPU 0405 (vangogh, LLVM 14.0.6, DRM 3.45, 5.13.0-valve36-1-neptune)",
    "gpuDriver": "4.6 (Compatibility Profile) Mesa 22.2.0 (git-17e5312102)",
    "kernel": "5.13.0-valve36-1-neptune",
    "notes": "Game is ridiculously simple & ridiculously fun. This IMO is PERFECT for the deck & a great game, 5/5",
    "os": "SteamOS Holo",
    "protonVersion": "9.0-1",
    "ram": "15 GB",
    "rating": "gold",
    "timestamp": 1715161971,
    "title": "",
    "source": "protondb"
  },
  {
    "appId": "2639810",
    "cpu": "Intel Core i5-10300H @ 2.50GHz",
    "duration": "underOneHour",
    "gpu": "Intel Mesa Intel UHD (CML GT2)",
    "gpuDriver": "4.6 Mesa 23.0.4-0ubuntu1~22.04.1",
    "kernel": "5.15.0-88-generic",
    "notes": "",
    "os": "Linux Mint 21.2",
    "protonVersion": "9.0-2",
    "ram": "16 GB",
    "rating": "gold",
    "timestamp": 1718922247,
    "title": "",
    "source": "protondb"
  },
  {
    "appId": "2639810",
    "cpu": "AMD Ryzen 7 5700U with Radeon Graphics",
    "duration": "underOneHour",
    "gpu": "AMD Radeon (radeonsi, renoir, LLVM 17.0.6, DRM 3.57, 6.9.3-060903-generic)",
    "gpuDriver": "4.6 Mesa 24.0.5-1ubuntu1",
    "kernel": "6.9.3-060903-generic",
    "notes": "Fun game overall, use mouse if you can't use keyboard.",
    "os": "Ubuntu 24.04 LTS",
    "protonVersion": "9.0-2",
    "ram": "14 GB",
    "rating": "silver",
    "timestamp": 1724683797,
    "title": "",
    "source": "protondb"
  }
]