[
  {
    "appId": "946610",
    "cpu": "Intel Core i7-8650U @ 1.90GHz",
    "duration": "aboutAnHour",
    "gpu": "Intel UHD 620 (Kabylake GT2)",
    "gpuDriver": "3.0 Mesa 18.2.8",
    "kernel": "4.15.0-50-generic",
    "os": "Ubuntu 18.04.2 LTS",
    "protonVersion": "4.2-7",
    "ram": "16 GB",
    "rating": "Gold",
    "timestamp": 1561299226,
    "title": "Pocket Rogues",
    "tweaks": {
      "useWineD3d11": true
    },
    "source": "protondb"
  },
  {
    "appId": "946610",
    "cpu": "Intel Atom x5-Z8350  @ 1.44GHz",
    "duration": "severalHours",
    "gpu": "Intel HD (Cherrytrail)",
    "gpuDriver": "3.0 Mesa 19.0.6",
    "kernel": "4.19.49-1-MANJARO",
    "notes": "The game runs perfeclty even on this very low end hardware, I encountered a freeze once but it lasted about 30 seconds and then the game continued like if nothing have happened, it may have just been my pc but other than that you can play the game perfectly.",
    "os": "Manjaro Linux",
    "protonVersion": "4.2-7",
    "ram": "4 GB",
    "rating": "Platinum",
    "timestamp": 1561329063,
    "title": "Pocket Rogues",
    "source": "protondb"
  },
  {
    "appId": "946610",
    "cpu": "Intel Core i3-7100 @ 3.90GHz",
    "duration": "lessThanFifteenMinutes",
    "gpu": "Intel HD 630 (Kaby Lake GT2)",
    "gpuDriver": "3.0 Mesa 18.2.8",
    "kernel": "4.15.0-52-generic",
    "notes": "The game is still in early access. It does not launch, just appears a window with a fast loading, then the game crashes. I've tested with proton 4.2-7 and 3.16, both had the same result. The game runs well if open the file \"Pocket Rogues.exe\" with Wine (I've tested with 4.0.1 version). It also runs in Windows wine steam client in Lutris. Using wine I had two problems: 1) the game freezes if you minimize the window; 2) the sound has some problems.",
    "os": "Linux Mint 19.1 Tessa",
    "protonVersion": "4.2-7",
    "ram": "4 GB",
    "rating": "Borked",
    "timestamp": 1561329412,
    "title": "Pocket Rogues",
    "source": "protondb"
  },
  {
    "appId": "946610",
    "cpu": "Intel Core i3-7100 @ 3.90GHz",
    "duration": "aboutAnHour",
    "gpu": "Intel HD 630 (Kaby Lake GT2)",
    "gpuDriver": "3.0 Mesa 18.2.8",
    "kernel": "4.15.0-54-generic",
    "notes": "The game runs perfectly out of the box. When I used proton in 4.2-7 version, the game did not launch, after update to 4.2-9 it runs flawlessly.",
    "os": "Linux Mint 19.1 Tessa",
    "protonVersion": "4.2-9",
    "protonVersionManual": "4.2-9",
    "ram": "4 GB",
    "rating": "Platinum",
    "timestamp": 1561758900,
    "title": "Pocket Rogues",
    "source": "protondb"
  }
]